setup.py
anecc/__init__.py
anecc/run.py
anecc.egg-info/PKG-INFO
anecc.egg-info/SOURCES.txt
anecc.egg-info/dependency_links.txt
anecc.egg-info/entry_points.txt
anecc.egg-info/requires.txt
anecc.egg-info/top_level.txt