Metadata-Version: 2.1
Name: anecc
Version: 1.0.8
Summary: ANE converter
Author: Eileen Yoon
Author-email: eyn@gmx.com
